colliderfeed/__init__.py
colliderfeed/collider_feed_config_private.py
colliderfeed/daemon.py
colliderfeed/fake_feed_daemon.py
colliderfeed-0.0.3.dist-info/METADATA
colliderfeed-0.0.3.dist-info/WHEEL
colliderfeed-0.0.3.dist-info/entry_points.txt
colliderfeed-0.0.3.dist-info/top_level.txt
colliderfeed-0.0.3.dist-info/RECORD
