Metadata-Version: 2.1
Name: colliderfeed
Version: 0.0.3
Summary: Data feed for Intech Supercollider contest
Home-page: https://github.com/microprediction/colliderfeed.git
Author: microprediction
Author-email: info@3za.org
License: MIT
Platform: UNKNOWN
Classifier: License :: OSI Approved :: MIT License
Classifier: Programming Language :: Python :: 3
Classifier: Programming Language :: Python :: 3.7
Requires-Dist: asyncio
Requires-Dist: aiohttp
Requires-Dist: requests
Requires-Dist: pathlib
Requires-Dist: retrying
